LICENSE.txt
MANIFEST.in
README.rst
requirements.txt
setup.py
test/test_coherent.py
test/test_incoherent.py
test/test_utils.py
tmmpy/__init__.py
tmmpy/examples.py
tmmpy/tmmpy_core.py
tmmpy/tmmpy_objects.py
tmmpy.egg-info/PKG-INFO
tmmpy.egg-info/SOURCES.txt
tmmpy.egg-info/dependency_links.txt
tmmpy.egg-info/requires.txt
tmmpy.egg-info/top_level.txt