Metadata-Version: 1.0
Name: tmmpy
Version: 0.0.9
Summary: Implementation of the tmm method along with different extensions, e.g. to deal with incoherence
Home-page: https://git.kern.phys.au.dk/SunTune/tmmpy/
Author: Emil Haldrup Eriksen
Author-email: emher@au.dk
License: MIT
Platform: any
